cosmicpi_web/__init__.py
cosmicpi_web/cli.py
cosmicpi_web/cosmicpi_web.py
cosmicpi_web/static/index.html
cosmicpi_web-0.2.1.dist-info/DESCRIPTION.rst
cosmicpi_web-0.2.1.dist-info/METADATA
cosmicpi_web-0.2.1.dist-info/RECORD
cosmicpi_web-0.2.1.dist-info/WHEEL
cosmicpi_web-0.2.1.dist-info/entry_points.txt
cosmicpi_web-0.2.1.dist-info/metadata.json
cosmicpi_web-0.2.1.dist-info/top_level.txt
