Metadata-Version: 2.0
Name: cosmicpi-web
Version: 0.2.1
Summary: Web frontend for Cosmic Pi
Home-page: https://github.com/CosmicPi/cosmicpi-web
Author: CosmicPi team
Author-email: info@cosmicpi.org
License: GNU General Public License v3
Keywords: cosmicpi_web
Platform: UNKNOWN
Classifier: Development Status :: 2 - Pre-Alpha
Classifier: Intended Audience :: Developers
Classifier: License :: OSI Approved :: GNU General Public License v3 (GPLv3)
Classifier: Natural Language :: English
Classifier: Programming Language :: Python :: 2
Classifier: Programming Language :: Python :: 2.6
Classifier: Programming Language :: Python :: 2.7
Classifier: Programming Language :: Python :: 3
Classifier: Programming Language :: Python :: 3.3
Classifier: Programming Language :: Python :: 3.4
Classifier: Programming Language :: Python :: 3.5
Requires-Dist: Click (>=6.0)
Requires-Dist: flask (>=0.11)
Requires-Dist: pika (>=0.10.0)
